{
  "openapi": "3.1.0",
  "info": {
    "title": "F1bot API",
    "version": "0.1.0"
  },
  "paths": {
    "/api/auth/login": {
      "post": {
        "tags": [
          "auth"
        ],
        "summary": "Login",
        "operationId": "login_api_auth_login_post",
        "requestBody": {
          "content": {
            "application/json": {
              "schema": {
                "$ref": "#/components/schemas/LoginRequest"
              }
            }
          },
          "required": true
        },
        "responses": {
          "200": {
            "description": "Successful Response",
            "content": {
              "application/json": {
                "schema": {
                  "$ref": "#/components/schemas/LoginResponse"
                }
              }
            }
          },
          "422": {
            "description": "Validation Error",
            "content": {
              "application/json": {
                "schema": {
                  "$ref": "#/components/schemas/HTTPValidationError"
                }
              }
            }
          }
        }
      }
    },
    "/api/auth/register": {
      "post": {
        "tags": [
          "auth"
        ],
        "summary": "Register",
        "operationId": "register_api_auth_register_post",
        "requestBody": {
          "content": {
            "application/json": {
              "schema": {
                "$ref": "#/components/schemas/RegisterRequest"
              }
            }
          },
          "required": true
        },
        "responses": {
          "200": {
            "description": "Successful Response",
            "content": {
              "application/json": {
                "schema": {
                  "$ref": "#/components/schemas/RegisterResponse"
                }
              }
            }
          },
          "422": {
            "description": "Validation Error",
            "content": {
              "application/json": {
                "schema": {
                  "$ref": "#/components/schemas/HTTPValidationError"
                }
              }
            }
          }
        }
      }
    },
    "/api/auth/session": {
      "get": {
        "tags": [
          "auth"
        ],
        "summary": "Get Session",
        "operationId": "get_session_api_auth_session_get",
        "responses": {
          "200": {
            "description": "Successful Response",
            "content": {
              "application/json": {
                "schema": {
                  "$ref": "#/components/schemas/SessionResponse"
                }
              }
            }
          }
        },
        "security": [
          {
            "BearerAuth": []
          }
        ],
        "parameters": []
      }
    },
    "/api/auth/logout": {
      "post": {
        "tags": [
          "auth"
        ],
        "summary": "Logout",
        "operationId": "logout_api_auth_logout_post",
        "responses": {
          "204": {
            "description": "Successful Response"
          }
        }
      }
    },
    "/api/health": {
      "get": {
        "tags": [
          "health"
        ],
        "summary": "Health Check",
        "operationId": "health_check_api_health_get",
        "responses": {
          "200": {
            "description": "Successful Response",
            "content": {
              "application/json": {
                "schema": {
                  "additionalProperties": true,
                  "type": "object",
                  "title": "Response Health Check Api Health Get"
                }
              }
            }
          }
        },
        "security": [
          {
            "BearerAuth": []
          }
        ]
      }
    },
    "/api/profile": {
      "get": {
        "tags": [
          "profile"
        ],
        "summary": "Get Profile",
        "operationId": "get_profile_api_profile_get",
        "responses": {
          "200": {
            "description": "Successful Response",
            "content": {
              "application/json": {
                "schema": {
                  "$ref": "#/components/schemas/BusinessProfile"
                }
              }
            }
          }
        },
        "security": [
          {
            "BearerAuth": []
          }
        ],
        "parameters": []
      },
      "put": {
        "tags": [
          "profile"
        ],
        "summary": "Upsert Profile",
        "operationId": "upsert_profile_api_profile_put",
        "requestBody": {
          "content": {
            "application/json": {
              "schema": {
                "$ref": "#/components/schemas/BusinessProfileUpsertRequest"
              }
            }
          },
          "required": true
        },
        "responses": {
          "200": {
            "description": "Successful Response",
            "content": {
              "application/json": {
                "schema": {
                  "$ref": "#/components/schemas/BusinessProfile"
                }
              }
            }
          },
          "422": {
            "description": "Validation Error",
            "content": {
              "application/json": {
                "schema": {
                  "$ref": "#/components/schemas/HTTPValidationError"
                }
              }
            }
          }
        },
        "security": [
          {
            "BearerAuth": []
          }
        ],
        "parameters": []
      }
    },
    "/api/leads/scan": {
      "post": {
        "tags": [
          "leads"
        ],
        "summary": "Scan Leads",
        "operationId": "scan_leads_api_leads_scan_post",
        "requestBody": {
          "content": {
            "application/json": {
              "schema": {
                "$ref": "#/components/schemas/LeadScanRequest"
              }
            }
          },
          "required": true
        },
        "responses": {
          "200": {
            "description": "Successful Response",
            "content": {
              "application/json": {
                "schema": {
                  "$ref": "#/components/schemas/LeadScanResponse"
                }
              }
            }
          },
          "422": {
            "description": "Validation Error",
            "content": {
              "application/json": {
                "schema": {
                  "$ref": "#/components/schemas/HTTPValidationError"
                }
              }
            }
          }
        },
        "security": [
          {
            "BearerAuth": []
          }
        ],
        "parameters": []
      }
    },
    "/api/leads": {
      "get": {
        "tags": [
          "leads"
        ],
        "summary": "List Leads",
        "operationId": "list_leads_api_leads_get",
        "security": [
          {
            "BearerAuth": []
          }
        ],
        "parameters": [
          {
            "name": "status",
            "in": "query",
            "required": false,
            "schema": {
              "anyOf": [
                {
                  "enum": [
                    "new",
                    "contacted",
                    "qualified",
                    "ignored"
                  ],
                  "type": "string"
                },
                {
                  "type": "null"
                }
              ],
              "title": "Status"
            }
          }
        ],
        "responses": {
          "200": {
            "description": "Successful Response",
            "content": {
              "application/json": {
                "schema": {
                  "$ref": "#/components/schemas/LeadListResponse"
                }
              }
            }
          },
          "422": {
            "description": "Validation Error",
            "content": {
              "application/json": {
                "schema": {
                  "$ref": "#/components/schemas/HTTPValidationError"
                }
              }
            }
          }
        }
      }
    },
    "/api/leads/export.csv": {
      "get": {
        "tags": [
          "leads"
        ],
        "summary": "Export Leads Csv",
        "operationId": "export_leads_csv_api_leads_export_csv_get",
        "security": [
          {
            "BearerAuth": []
          }
        ],
        "parameters": [
          {
            "name": "status",
            "in": "query",
            "required": false,
            "schema": {
              "anyOf": [
                {
                  "enum": [
                    "new",
                    "contacted",
                    "qualified",
                    "ignored"
                  ],
                  "type": "string"
                },
                {
                  "type": "null"
                }
              ],
              "title": "Status"
            }
          }
        ],
        "responses": {
          "200": {
            "description": "Successful Response",
            "content": {
              "text/plain": {
                "schema": {
                  "type": "string"
                }
              }
            }
          },
          "422": {
            "description": "Validation Error",
            "content": {
              "application/json": {
                "schema": {
                  "$ref": "#/components/schemas/HTTPValidationError"
                }
              }
            }
          }
        }
      }
    },
    "/api/leads/{lead_id}": {
      "get": {
        "tags": [
          "leads"
        ],
        "summary": "Get Lead",
        "operationId": "get_lead_api_leads__lead_id__get",
        "security": [
          {
            "BearerAuth": []
          }
        ],
        "parameters": [
          {
            "name": "lead_id",
            "in": "path",
            "required": true,
            "schema": {
              "type": "string",
              "title": "Lead Id"
            }
          }
        ],
        "responses": {
          "200": {
            "description": "Successful Response",
            "content": {
              "application/json": {
                "schema": {
                  "$ref": "#/components/schemas/LeadRecord"
                }
              }
            }
          },
          "422": {
            "description": "Validation Error",
            "content": {
              "application/json": {
                "schema": {
                  "$ref": "#/components/schemas/HTTPValidationError"
                }
              }
            }
          }
        }
      }
    },
    "/api/leads/{lead_id}/status": {
      "patch": {
        "tags": [
          "leads"
        ],
        "summary": "Update Lead Status",
        "operationId": "update_lead_status_api_leads__lead_id__status_patch",
        "security": [
          {
            "BearerAuth": []
          }
        ],
        "parameters": [
          {
            "name": "lead_id",
            "in": "path",
            "required": true,
            "schema": {
              "type": "string",
              "title": "Lead Id"
            }
          }
        ],
        "requestBody": {
          "required": true,
          "content": {
            "application/json": {
              "schema": {
                "$ref": "#/components/schemas/LeadStatusUpdateRequest"
              }
            }
          }
        },
        "responses": {
          "200": {
            "description": "Successful Response",
            "content": {
              "application/json": {
                "schema": {
                  "$ref": "#/components/schemas/LeadRecord"
                }
              }
            }
          },
          "422": {
            "description": "Validation Error",
            "content": {
              "application/json": {
                "schema": {
                  "$ref": "#/components/schemas/HTTPValidationError"
                }
              }
            }
          }
        }
      }
    },
    "/api/settings": {
      "get": {
        "tags": [
          "settings"
        ],
        "summary": "Get Runtime Settings",
        "operationId": "get_runtime_settings_api_settings_get",
        "responses": {
          "200": {
            "description": "Successful Response",
            "content": {
              "application/json": {
                "schema": {
                  "additionalProperties": {
                    "anyOf": [
                      {
                        "type": "boolean"
                      },
                      {
                        "type": "string"
                      },
                      {
                        "type": "integer"
                      }
                    ]
                  },
                  "type": "object",
                  "title": "Response Get Runtime Settings Api Settings Get"
                }
              }
            }
          }
        },
        "security": [
          {
            "BearerAuth": []
          }
        ],
        "parameters": []
      }
    },
    "/": {
      "get": {
        "summary": "Root",
        "operationId": "root__get",
        "responses": {
          "200": {
            "description": "Successful Response",
            "content": {
              "application/json": {
                "schema": {
                  "additionalProperties": {
                    "type": "string"
                  },
                  "type": "object",
                  "title": "Response Root  Get"
                }
              }
            }
          }
        }
      }
    }
  },
  "components": {
    "schemas": {
      "BusinessProfile": {
        "properties": {
          "user_id": {
            "type": "string",
            "title": "User Id"
          },
          "business_description": {
            "type": "string",
            "maxLength": 2000,
            "minLength": 10,
            "title": "Business Description"
          },
          "keywords": {
            "items": {
              "type": "string"
            },
            "type": "array",
            "title": "Keywords"
          },
          "subreddits": {
            "items": {
              "type": "string"
            },
            "type": "array",
            "title": "Subreddits"
          },
          "updated_at": {
            "anyOf": [
              {
                "type": "string",
                "format": "date-time"
              },
              {
                "type": "null"
              }
            ],
            "title": "Updated At"
          }
        },
        "type": "object",
        "required": [
          "user_id",
          "business_description"
        ],
        "title": "BusinessProfile"
      },
      "BusinessProfileUpsertRequest": {
        "properties": {
          "business_description": {
            "type": "string",
            "maxLength": 2000,
            "minLength": 10,
            "title": "Business Description"
          },
          "keywords": {
            "items": {
              "type": "string"
            },
            "type": "array",
            "title": "Keywords"
          },
          "subreddits": {
            "items": {
              "type": "string"
            },
            "type": "array",
            "title": "Subreddits"
          }
        },
        "type": "object",
        "required": [
          "business_description"
        ],
        "title": "BusinessProfileUpsertRequest"
      },
      "CandidatePost": {
        "properties": {
          "id": {
            "type": "string",
            "title": "Id"
          },
          "title": {
            "type": "string",
            "title": "Title"
          },
          "body": {
            "type": "string",
            "title": "Body"
          },
          "subreddit": {
            "type": "string",
            "title": "Subreddit"
          },
          "url": {
            "type": "string",
            "title": "Url"
          },
          "author": {
            "type": "string",
            "title": "Author"
          },
          "created_utc": {
            "type": "string",
            "format": "date-time",
            "title": "Created Utc"
          },
          "score": {
            "type": "integer",
            "title": "Score"
          },
          "num_comments": {
            "type": "integer",
            "title": "Num Comments"
          }
        },
        "type": "object",
        "required": [
          "id",
          "title",
          "body",
          "subreddit",
          "url",
          "author",
          "created_utc",
          "score",
          "num_comments"
        ],
        "title": "CandidatePost"
      },
      "HTTPValidationError": {
        "properties": {
          "detail": {
            "items": {
              "$ref": "#/components/schemas/ValidationError"
            },
            "type": "array",
            "title": "Detail"
          }
        },
        "type": "object",
        "title": "HTTPValidationError"
      },
      "LeadInsight": {
        "properties": {
          "post": {
            "$ref": "#/components/schemas/CandidatePost"
          },
          "lead_score": {
            "type": "number",
            "maximum": 100.0,
            "minimum": 0.0,
            "title": "Lead Score"
          },
          "qualification_reason": {
            "type": "string",
            "title": "Qualification Reason"
          },
          "suggested_outreach": {
            "type": "string",
            "title": "Suggested Outreach"
          }
        },
        "type": "object",
        "required": [
          "post",
          "lead_score",
          "qualification_reason",
          "suggested_outreach"
        ],
        "title": "LeadInsight"
      },
      "LeadListResponse": {
        "properties": {
          "leads": {
            "items": {
              "$ref": "#/components/schemas/LeadRecord"
            },
            "type": "array",
            "title": "Leads"
          }
        },
        "type": "object",
        "required": [
          "leads"
        ],
        "title": "LeadListResponse"
      },
      "LeadRecord": {
        "properties": {
          "id": {
            "type": "string",
            "title": "Id"
          },
          "user_id": {
            "type": "string",
            "title": "User Id"
          },
          "status": {
            "type": "string",
            "enum": [
              "new",
              "contacted",
              "qualified",
              "ignored"
            ],
            "title": "Status",
            "default": "new"
          },
          "post": {
            "$ref": "#/components/schemas/CandidatePost"
          },
          "lead_score": {
            "type": "number",
            "maximum": 100.0,
            "minimum": 0.0,
            "title": "Lead Score"
          },
          "qualification_reason": {
            "type": "string",
            "title": "Qualification Reason"
          },
          "suggested_outreach": {
            "type": "string",
            "title": "Suggested Outreach"
          },
          "scan_id": {
            "type": "string",
            "title": "Scan Id"
          },
          "created_at": {
            "type": "string",
            "format": "date-time",
            "title": "Created At"
          },
          "updated_at": {
            "type": "string",
            "format": "date-time",
            "title": "Updated At"
          }
        },
        "type": "object",
        "required": [
          "id",
          "user_id",
          "post",
          "lead_score",
          "qualification_reason",
          "suggested_outreach",
          "scan_id",
          "created_at",
          "updated_at"
        ],
        "title": "LeadRecord"
      },
      "LeadScanRequest": {
        "properties": {
          "business_description": {
            "type": "string",
            "maxLength": 2000,
            "minLength": 10,
            "title": "Business Description"
          },
          "keywords": {
            "items": {
              "type": "string"
            },
            "type": "array",
            "title": "Keywords"
          },
          "subreddits": {
            "items": {
              "type": "string"
            },
            "type": "array",
            "title": "Subreddits"
          },
          "limit": {
            "type": "integer",
            "maximum": 100.0,
            "minimum": 1.0,
            "title": "Limit",
            "default": 20
          }
        },
        "type": "object",
        "required": [
          "business_description"
        ],
        "title": "LeadScanRequest"
      },
      "LeadScanResponse": {
        "properties": {
          "leads": {
            "items": {
              "$ref": "#/components/schemas/LeadInsight"
            },
            "type": "array",
            "title": "Leads"
          },
          "total_candidates": {
            "type": "integer",
            "title": "Total Candidates"
          },
          "used_ai": {
            "type": "boolean",
            "title": "Used Ai"
          }
        },
        "type": "object",
        "required": [
          "leads",
          "total_candidates",
          "used_ai"
        ],
        "title": "LeadScanResponse"
      },
      "LeadStatusUpdateRequest": {
        "properties": {
          "status": {
            "type": "string",
            "enum": [
              "new",
              "contacted",
              "qualified",
              "ignored"
            ],
            "title": "Status"
          }
        },
        "type": "object",
        "required": [
          "status"
        ],
        "title": "LeadStatusUpdateRequest"
      },
      "LoginRequest": {
        "properties": {
          "email": {
            "type": "string",
            "format": "email",
            "title": "Email"
          },
          "password": {
            "type": "string",
            "maxLength": 128,
            "minLength": 10,
            "title": "Password"
          }
        },
        "type": "object",
        "required": [
          "email",
          "password"
        ],
        "title": "LoginRequest"
      },
      "LoginResponse": {
        "properties": {
          "user_id": {
            "type": "string",
            "title": "User Id"
          },
          "email": {
            "type": "string",
            "title": "Email"
          },
          "access_token": {
            "type": "string",
            "title": "Access Token"
          },
          "token_type": {
            "type": "string",
            "title": "Token Type",
            "default": "bearer"
          }
        },
        "type": "object",
        "required": [
          "user_id",
          "email",
          "access_token"
        ],
        "title": "LoginResponse"
      },
      "RegisterRequest": {
        "properties": {
          "email": {
            "type": "string",
            "format": "email",
            "title": "Email"
          },
          "password": {
            "type": "string",
            "maxLength": 128,
            "minLength": 10,
            "title": "Password"
          },
          "full_name": {
            "anyOf": [
              {
                "type": "string",
                "maxLength": 120
              },
              {
                "type": "null"
              }
            ],
            "title": "Full Name"
          }
        },
        "type": "object",
        "required": [
          "email",
          "password"
        ],
        "title": "RegisterRequest"
      },
      "RegisterResponse": {
        "properties": {
          "user_id": {
            "type": "string",
            "title": "User Id"
          },
          "email": {
            "type": "string",
            "title": "Email"
          },
          "access_token": {
            "type": "string",
            "title": "Access Token"
          },
          "token_type": {
            "type": "string",
            "title": "Token Type",
            "default": "bearer"
          }
        },
        "type": "object",
        "required": [
          "user_id",
          "email",
          "access_token"
        ],
        "title": "RegisterResponse"
      },
      "SessionResponse": {
        "properties": {
          "user_id": {
            "type": "string",
            "title": "User Id"
          },
          "email": {
            "type": "string",
            "title": "Email"
          }
        },
        "type": "object",
        "required": [
          "user_id",
          "email"
        ],
        "title": "SessionResponse"
      },
      "ValidationError": {
        "properties": {
          "loc": {
            "items": {
              "anyOf": [
                {
                  "type": "string"
                },
                {
                  "type": "integer"
                }
              ]
            },
            "type": "array",
            "title": "Location"
          },
          "msg": {
            "type": "string",
            "title": "Message"
          },
          "type": {
            "type": "string",
            "title": "Error Type"
          }
        },
        "type": "object",
        "required": [
          "loc",
          "msg",
          "type"
        ],
        "title": "ValidationError"
      }
    },
    "securitySchemes": {
      "BearerAuth": {
        "type": "http",
        "scheme": "bearer",
        "bearerFormat": "JWT",
        "description": "JWT access token obtained from /api/auth/login or /api/auth/register."
      }
    }
  }
}